<?xml version="1.0" encoding="utf-8" ?><dwsync><file name="mem.emoney.php" server="loosfly.com//" local="3497241917" remote="319783739114088688" Dst="-1" /><file name="indb.excel.mem.emoney.php" server="loosfly.com//" local="3497241917" remote="319783739114088688" Dst="-1" /><file name="statistics.sales.day.php" server="loosfly.com//" local="3497241917" remote="319783739110200688" Dst="-1" /><file name="indb.excel.popu.cart.php" server="loosfly.com//" local="3497241917" remote="319783739113829488" Dst="-1" /><file name="indb.excel.popu.pageview.php" server="loosfly.com//" local="3497241917" remote="319783739113829488" Dst="-1" /><file name="indb.excel.popu.wishlist.php" server="loosfly.com//" local="3497241917" remote="319783739113829488" Dst="-1" /><file name="popu.cart.php" server="loosfly.com//" local="3497241917" remote="319783739113829488" Dst="-1" /><file name="popu.pageview.php" server="loosfly.com//" local="3497241917" remote="319783739113829488" Dst="-1" /><file name="popu.wishlist.php" server="loosfly.com//" local="3497241917" remote="319783739113829488" Dst="-1" /></dwsync>