<?xml version="1.0" encoding="utf-8" ?><dwsync><file name="_db.patch.php" server="loosfly.com//" local="3497241886" remote="319783739119359088" Dst="-1" /><file name="_header.php" server="loosfly.com//" local="3497241887" remote="319783739120136688" Dst="-1" /><file name="blank.php" server="loosfly.com//" local="3432121200" remote="318763443825017712" Dst="-1" /><file name="dbconn.php" server="loosfly.com//" local="3435318000" remote="318763443828214512" Dst="-1" /><file name="enamooInstall.txt" server="loosfly.com//" local="3432121200" remote="318763443825017712" Dst="-1" /><file name="freessl.php" server="loosfly.com//" local="3432121200" remote="318763443825017712" Dst="-1" /><file name="index.php" server="loosfly.com//" local="3446722800" remote="318763443839619312" Dst="-1" /><file name="intact.frameset.php" server="loosfly.com//" local="3447414000" remote="318763443840310512" Dst="-1" /></dwsync>